mcp_server_gemini_image_generator/__init__.py
mcp_server_gemini_image_generator/prompts.py
mcp_server_gemini_image_generator/server.py
mcp_server_gemini_image_generator/utils.py
iflow_mcp_mcp_server_gemini_image_generator-0.1.0.dist-info/METADATA
iflow_mcp_mcp_server_gemini_image_generator-0.1.0.dist-info/WHEEL
iflow_mcp_mcp_server_gemini_image_generator-0.1.0.dist-info/entry_points.txt
iflow_mcp_mcp_server_gemini_image_generator-0.1.0.dist-info/licenses/LICENSE
iflow_mcp_mcp_server_gemini_image_generator-0.1.0.dist-info/RECORD
