Metadata-Version: 2.4
Name: iflow-mcp_mcp-server-gemini-image-generator
Version: 0.1.0
Author-email: bongki Lee <qhdrl12@gmail.com>
License: MIT
License-File: LICENSE
Keywords: automation,http,llm,mcp
Requires-Python: >=3.11
Requires-Dist: fastmcp>=0.4.1
Requires-Dist: google-genai>=1.7.0
Requires-Dist: google>=3.0.0
Requires-Dist: pillow>=11.1.0
